[
  {
    "employer_name": "Google",
    "job_title": "Data Center Hardware Operations Manager",
    "job_city": "Austell",
    "job_state": "GA",
    "job_posted_at": "Recently",
    "job_description": "28 Category: Hardware Engineering. Level: corporate_fareGoogle. Posted: Recently. Full Title: Data Center Hardware Operations Manager",
    "job_apply_link": "https://www.google.com/about/careers/applications/jobs/results/106920192365208262-data-center-hardware-operations-manager?q=%22Hardware+Engineering%22&location=United+States&target_level=INTERN_AND_APPRENTICE&target_level=EARLY&target_level=ADVANCED&target_level=MID&degree=MASTERS&degree=ASSOCIATE&degree=BACHELORS&employment_type=TEMPORARY&employment_type=INTERN&employment_type=PART_TIME&employment_type=FULL_TIME&page=2",
    "id": "google-data-center-hardware-operations-manager-austell"
  },
  {
    "employer_name": "Arm",
    "job_title": "Graduate Hardware Engineer",
    "job_city": "Multiple",
    "job_state": "Locations",
    "job_posted_at": "Recently",
    "job_description": "Hardware Engineering job for the role Graduate Hardware Engineer at Multiple locations",
    "job_apply_link": "https://careers.arm.com/job/austin/graduate-hardware-engineer/33099/85997348720",
    "id": "arm-graduate-hardware-engineer-multiple"
  }
]