[
  {
    "employer_name": "AiJobs",
    "job_title": "Software Architect, AI Networking",
    "job_city": "Santa Clara",
    "job_state": "CA",
    "job_posted_at": "1d ago",
    "job_description": "hardware engineering job for the role Senior Software Architect, AI Networking at US, CA, Santa Clara",
    "job_apply_link": "https://www.aijobs.com/jobs/180621180-senior-software-architect-ai-networking",
    "id": "aijobs-software-architect-ai-networking-santa-clara"
  },
  {
    "employer_name": "AiJobs",
    "job_title": "Software Engineer, AI Inference Systems",
    "job_city": "Santa Clara",
    "job_state": "CA",
    "job_posted_at": "1d ago",
    "job_description": "hardware engineering job for the role Senior Software Engineer, AI Inference Systems at US, CA, Santa Clara",
    "job_apply_link": "https://www.aijobs.com/jobs/180621177-senior-software-engineer-ai-inference-systems",
    "id": "aijobs-software-engineer-ai-inference-systems-santa-clara"
  }
]