[
  {
    "employer_name": "Micron",
    "job_title": "Module Validation Developer",
    "job_city": "Boise",
    "job_state": "Idaho",
    "job_posted_at": "Posted a day ago",
    "job_description": "hardware engineering job for the role Staff Module Validation Developer at Boise, Idaho, United States of America",
    "job_apply_link": "https://careers.micron.com/careers/job/38467305",
    "id": "micron-module-validation-developer-boise"
  },
  {
    "employer_name": "MARVELL",
    "job_title": "Advanced Packaging SI/PI Staff Engineer",
    "job_city": "2 Locations",
    "job_state": "",
    "job_posted_at": "Posted Today",
    "job_description": "hardware engineering job for the role Advanced Packaging SI/PI Staff Engineer at 2 Locations",
    "job_apply_link": "https://marvell.wd1.myworkdayjobs.com/en-US/MarvellCareers/job/Westborough-MA/Advanced-Packaging-SI-PI-Staff-Engineer_2503128?q=hardware+engineering&Country=bc33aa3152ec42d4995f4791a106ed09",
    "id": "marvell-advanced-packaging-si-pi-staff-engineer-2-locations"
  }
]