[
  {
    "job_title": "Project Design Mechanical Engineer, Fleet Remediation Engineering",
    "employer_name": "Amazon",
    "job_city": "Columbus",
    "job_state": "OH",
    "job_description": "hardware engineering job for the role Project Design Mechanical Engineer, Fleet Remediation Engineering at Columbus, OH, USA",
    "job_apply_link": "https://amazon.jobs/en-gb/jobs/3117557/project-design-mechanical-engineer-fleet-remediation-engineering",
    "job_posted_at": "2025-10-29T17:27:46.368Z",
    "job_posted_at_datetime_utc": "2025-10-29T17:27:46.368Z",
    "id": "amazon-project-design-mechanical-engineer-fleet-remediation-engineering-columbus"
  }
]