[
  {
    "employer_name": "Arm",
    "job_title": "Failure Analysis Engineer",
    "job_city": "Hsinchu",
    "job_state": "Taiwan",
    "job_posted_at": "Recently",
    "job_description": "Hardware Engineering job for the role Staff Failure Analysis Engineer at Hsinchu, Taiwan",
    "job_apply_link": "https://careers.arm.com/job/hsinchu/staff-failure-analysis-engineer/33099/86312145488",
    "id": "arm-failure-analysis-engineer-hsinchu"
  },
  {
    "employer_name": "Arm",
    "job_title": "FPGA/CPLD Design Engineer",
    "job_city": "Bengaluru",
    "job_state": "India",
    "job_posted_at": "Recently",
    "job_description": "Hardware Engineering job for the role Senior FPGA/CPLD Design Engineer at Bengaluru, India",
    "job_apply_link": "https://careers.arm.com/job/bengaluru/senior-fpga-cpld-design-engineer/33099/87260510944",
    "id": "arm-fpga-cpld-design-engineer-bengaluru"
  },
  {
    "employer_name": "Arm",
    "job_title": "Partner Program Manager",
    "job_city": "Multiple",
    "job_state": "Locations",
    "job_posted_at": "Recently",
    "job_description": "Hardware Engineering job for the role Principal Partner Program Manager at Multiple locations",
    "job_apply_link": "https://careers.arm.com/job/austin/principal-partner-program-manager/33099/87011765776",
    "id": "arm-partner-program-manager-multiple"
  },
  {
    "employer_name": "Arm",
    "job_title": "Multimedia Solution Manager",
    "job_city": "Multiple",
    "job_state": "Locations",
    "job_posted_at": "Recently",
    "job_description": "Hardware Engineering job for the role Multimedia Solution Manager at Multiple locations",
    "job_apply_link": "https://careers.arm.com/job/cambridge/multimedia-solution-manager/33099/76633282320",
    "id": "arm-multimedia-solution-manager-multiple"
  },
  {
    "employer_name": "Arm",
    "job_title": "Digital Interviews at Arm",
    "job_city": "Multiple",
    "job_state": "Locations",
    "job_posted_at": "Recently",
    "job_description": "Hardware Engineering job for the role Digital Interviews at Arm at ",
    "job_apply_link": "https://careers.arm.com/digital-interviews-at-arm",
    "id": "arm-digital-interviews-at-arm-multiple"
  },
  {
    "employer_name": "Arm",
    "job_title": "Dekel's Story",
    "job_city": "Multiple",
    "job_state": "Locations",
    "job_posted_at": "Recently",
    "job_description": "Hardware Engineering job for the role Dekel's Story at ",
    "job_apply_link": "https://careers.arm.com/dekel-hasid-story",
    "id": "arm-dekel-s-story-multiple"
  },
  {
    "employer_name": "Arm",
    "job_title": "Arm Cambridge Office",
    "job_city": "Multiple",
    "job_state": "Locations",
    "job_posted_at": "Recently",
    "job_description": "Hardware Engineering job for the role Arm Cambridge Office at ",
    "job_apply_link": "https://careers.arm.com/uk-cambridge-office",
    "id": "arm-arm-cambridge-office-multiple"
  },
  {
    "employer_name": "Arm",
    "job_title": "Arm Munich Office",
    "job_city": "Multiple",
    "job_state": "Locations",
    "job_posted_at": "Recently",
    "job_description": "Hardware Engineering job for the role Arm Munich Office at ",
    "job_apply_link": "https://careers.arm.com/germany-munich",
    "id": "arm-arm-munich-office-multiple"
  },
  {
    "employer_name": "Arm",
    "job_title": "Augustina's Story",
    "job_city": "Multiple",
    "job_state": "Locations",
    "job_posted_at": "Recently",
    "job_description": "Hardware Engineering job for the role Augustina's Story at ",
    "job_apply_link": "https://careers.arm.com/augustina-adjei-makers-women-in-software-awards",
    "id": "arm-augustina-s-story-multiple"
  },
  {
    "employer_name": "Arm",
    "job_title": "Conall's Story",
    "job_city": "Multiple",
    "job_state": "Locations",
    "job_posted_at": "Recently",
    "job_description": "Hardware Engineering job for the role Conall's Story at ",
    "job_apply_link": "https://careers.arm.com/intern-to-graduate-conall-farney",
    "id": "arm-conall-s-story-multiple"
  },
  {
    "employer_name": "Arm",
    "job_title": "Graduate Program at Arm | You X Arm",
    "job_city": "Multiple",
    "job_state": "Locations",
    "job_posted_at": "Recently",
    "job_description": "Hardware Engineering job for the role Graduate Program at Arm | You X Arm at ",
    "job_apply_link": "https://careers.arm.com/graduates",
    "id": "arm-graduate-program-at-arm-you-x-arm-multiple"
  },
  {
    "employer_name": "Arm",
    "job_title": "Life at Arm",
    "job_city": "Multiple",
    "job_state": "Locations",
    "job_posted_at": "Recently",
    "job_description": "Hardware Engineering job for the role Life at Arm at ",
    "job_apply_link": "https://careers.arm.com/life-at-arm",
    "id": "arm-life-at-arm-multiple"
  }
]