[
  {
    "job_title": "Cleared Data Center Mechanical Field Engineer, ADC Field Engineering, Field Engineering",
    "employer_name": "Amazon",
    "job_city": "Aurora",
    "job_state": "CO",
    "job_description": "hardware engineering job for the role Cleared Data Center Mechanical Field Engineer, ADC Field Engineering, Field Engineering at Aurora, CO, USA",
    "job_apply_link": "https://amazon.jobs/en-gb/jobs/3181383/cleared-data-center-mechanical-field-engineer-adc-field-engineering-field-engineering",
    "job_posted_at": "2026-02-14T02:10:09.854Z",
    "job_posted_at_datetime_utc": "2026-02-14T02:10:09.854Z",
    "id": "amazon-cleared-data-center-mechanical-field-engineer-adc-field-engineering-field-engineering-aurora"
  }
]