[
  {
    "employer_name": "Arm",
    "job_title": "CPU Performance – Microarchitecture Exploration Engineer",
    "job_city": "Austin",
    "job_state": "Texas",
    "job_posted_at": "Recently",
    "job_description": "Hardware Engineering job for the role CPU Performance – Microarchitecture Exploration Engineer at Austin, Texas",
    "job_apply_link": "https://careers.arm.com/job/austin/cpu-performance-microarchitecture-exploration-engineer/33099/86865038384",
    "id": "arm-cpu-performance-microarchitecture-exploration-engineer-austin"
  }
]