[
  {
    "job_title": "Manufacturing Engineer Manager – Space Hardware - 2nd Shift, Amazon Leo",
    "employer_name": "Amazon",
    "job_city": "Merritt Island",
    "job_state": "FL",
    "job_description": "hardware engineering job for the role Manufacturing Engineer Manager – Space Hardware - 2nd Shift, Amazon Leo at Merritt Island, FL, USA",
    "job_apply_link": "https://amazon.jobs/en-gb/jobs/3195134/manufacturing-engineer-manager-space-hardware-2nd-shift-amazon-leo",
    "job_posted_at": "2026-03-03T23:55:09.080Z",
    "job_posted_at_datetime_utc": "2026-03-03T23:55:09.080Z",
    "id": "amazon-manufacturing-engineer-manager-space-hardware-2nd-shift-amazon-leo-merritt-island"
  },
  {
    "employer_name": "Micron",
    "job_title": "Engineer, HIG HMB Architecture",
    "job_city": "Richardson",
    "job_state": "Texas",
    "job_posted_at": "Posted a day ago",
    "job_description": "hardware engineering job for the role Principal Engineer, HIG HMB Architecture at Richardson, Texas, United States of America + 1 more",
    "job_apply_link": "https://careers.micron.com/careers/job/40521201",
    "id": "micron-engineer-hig-hmb-architecture-richardson"
  },
  {
    "employer_name": "IBM",
    "job_title": "SMPO Solutions Specialist",
    "job_city": "WASHINGTON",
    "job_state": "US",
    "job_posted_at": "Recently",
    "job_description": "Hardware Engineering job for the role SMPO Solutions Specialist at ProfessionalWASHINGTON, US",
    "job_apply_link": "https://careers.ibm.com/careers/JobDetail?jobId=97889&source=WEB_Search_NA",
    "id": "ibm-smpo-solutions-specialist-washington"
  }
]