[
  {
    "employer_name": "Arm",
    "job_title": "Senior/Staff/Principal Verification Engineer - Video",
    "job_city": "Cambridge",
    "job_state": "United Kingdom",
    "job_posted_at": "Recently",
    "job_description": "Hardware Engineering job for the role Senior/Staff/Principal Verification Engineer - Video at Cambridge, United Kingdom, Bristol, United Kingdom",
    "job_apply_link": "https://careers.arm.com/job/cambridge/senior-staff-principal-verification-engineer-video/33099/84401268624",
    "id": "arm-senior-staff-principal-verification-engineer-video-cambridge"
  },
  {
    "employer_name": "ABB",
    "job_title": "R&D Senior Engineer - MV Switchgear",
    "job_city": "Mebane",
    "job_state": "North Carolina",
    "job_posted_at": "1 day ago",
    "job_description": "hardware engineering job for the role R&D Senior Engineer - MV Switchgear at Mebane, North Carolina, United States of America",
    "job_apply_link": "https://careers.abb/global/en/job/JR00016005/R-D-Senior-Engineer-MV-Switchgear",
    "id": "abb-r-d-senior-engineer-mv-switchgear-mebane"
  }
]