[
  {
    "employer_name": "ABB",
    "job_title": "SW/FW Senior R&D Engineer for SST (80-100%)",
    "job_city": "Baden-Daettwil",
    "job_state": "Aargau",
    "job_posted_at": "Today",
    "job_description": "hardware engineering job for the role SW/FW Senior R&D Engineer for SST (80-100%) at Baden-Daettwil, Aargau, Switzerland",
    "job_apply_link": "https://careers.abb/global/en/job/JR00018307/SW-FW-Senior-R-D-Engineer-for-SST-80-100",
    "id": "abb-sw-fw-senior-r-d-engineer-for-sst-80-100-baden-daettwil"
  }
]