[
  {
    "employer_name": "ANALOG DEVICES",
    "job_title": "Systems Application Engineer",
    "job_city": "US",
    "job_state": "MA",
    "job_posted_at": "Posted Today",
    "job_description": "hardware engineering job for the role Principal Systems Application Engineer at US, MA, Wilmington",
    "job_apply_link": "https://analogdevices.wd1.myworkdayjobs.com/en-US/External/job/US-MA-Wilmington/Principal-Systems-Application-Engineer_R256172?q=hardware+engineering&locationCountry=bc33aa3152ec42d4995f4791a106ed09",
    "id": "analog-devices-systems-application-engineer-us"
  }
]