[
  {
    "employer_name": "AiJobs",
    "job_title": "Electrical Engineering Intern",
    "job_city": "Unknown",
    "job_state": "US",
    "job_posted_at": "1d ago",
    "job_description": "hardware engineering job for the role Electrical Engineering Intern at ",
    "job_apply_link": "https://www.aijobs.com/jobs/226423570-electrical-engineering-intern",
    "id": "aijobs-electrical-engineering-intern-unknown"
  },
  {
    "employer_name": "AiJobs",
    "job_title": "Device Software Engineering Intern",
    "job_city": "Unknown",
    "job_state": "US",
    "job_posted_at": "1d ago",
    "job_description": "hardware engineering job for the role Device Software Engineering Intern at ",
    "job_apply_link": "https://www.aijobs.com/jobs/226423571-device-software-engineering-intern",
    "id": "aijobs-device-software-engineering-intern-unknown"
  },
  {
    "employer_name": "AiJobs",
    "job_title": "Device Quality Assurance Intern",
    "job_city": "Unknown",
    "job_state": "US",
    "job_posted_at": "1d ago",
    "job_description": "hardware engineering job for the role Device Quality Assurance Intern at ",
    "job_apply_link": "https://www.aijobs.com/jobs/226423568-device-quality-assurance-intern",
    "id": "aijobs-device-quality-assurance-intern-unknown"
  },
  {
    "employer_name": "AiJobs",
    "job_title": "Mechanical Engineer Intern",
    "job_city": "Unknown",
    "job_state": "US",
    "job_posted_at": "1d ago",
    "job_description": "hardware engineering job for the role Mechanical Engineer Intern at ",
    "job_apply_link": "https://www.aijobs.com/jobs/226423569-mechanical-engineer-intern",
    "id": "aijobs-mechanical-engineer-intern-unknown"
  },
  {
    "employer_name": "AiJobs",
    "job_title": "Site Reliability Engineering Intern",
    "job_city": "Unknown",
    "job_state": "US",
    "job_posted_at": "1d ago",
    "job_description": "hardware engineering job for the role Site Reliability Engineering Intern at ",
    "job_apply_link": "https://www.aijobs.com/jobs/226423567-site-reliability-engineering-intern",
    "id": "aijobs-site-reliability-engineering-intern-unknown"
  }
]